cyberchipped/__init__.py
cyberchipped/ai.py
cyberchipped-2.2.0.dist-info/LICENSE
cyberchipped-2.2.0.dist-info/METADATA
cyberchipped-2.2.0.dist-info/WHEEL
cyberchipped-2.2.0.dist-info/RECORD
