Metadata-Version: 2.3
Name: cyberchipped
Version: 2.2.0
Summary: Build AI Assistants Fast
License: MIT
Keywords: ai,openai
Author: Bevan Hunt
Author-email: bevan@bevanhunt.com
Requires-Python: >=3.9,<4.0
Classifier: License :: OSI Approved :: MIT License
Classifier: Programming Language :: Python :: 3
Classifier: Programming Language :: Python :: 3.9
Classifier: Programming Language :: Python :: 3.10
Classifier: Programming Language :: Python :: 3.11
Classifier: Programming Language :: Python :: 3.12
Classifier: Programming Language :: Python :: 3.13
Classifier: Programming Language :: Python :: 3 :: Only
Classifier: Topic :: Scientific/Engineering :: Artificial Intelligence
Requires-Dist: aiosqlite (>=0.20.0,<0.21.0)
Requires-Dist: motor (>=3.7.0,<4.0.0)
Requires-Dist: openai (>=1.61.0,<2.0.0)
Requires-Dist: pydantic (>=2.10.6,<3.0.0)
Project-URL: Repository, https://github.com/truemagic-coder/cyberchipped
